setup.py
ParallelThreading/setup.py
ParallelThreading.egg-info/PKG-INFO
ParallelThreading.egg-info/SOURCES.txt
ParallelThreading.egg-info/dependency_links.txt
ParallelThreading.egg-info/top_level.txt