Metadata-Version: 1.0
Name: ParallelThreading
Version: 0.7
Summary: Parallel Process Threading
Home-page: https://github.com/user/Python-Alex
Author: Python Alex
Author-email: obfuscate@riseup.net
License: MIT
Keywords: parallel,nonblocking,closeasync,threading,processing,cpu,python,processes
Platform: UNKNOWN
